{
  "drink": [
    {
      "id": "masala-chai",
      "name": "Masala Chai",
      "serving": 1,
      "ingredients": [
        {
          "quantity": "1 cup",
          "name": "water"
        },
        {
          "quantity": "1.5 tsp",
          "name": "sugar"
        },
        {
          "quantity": "0.25 tsp",
          "name": "cardamom"
        },
        {
          "quantity": "0.25 tsp",
          "name": "clove"
        },
        {
          "quantity": "0.25 tsp",
          "name": "black peppercorn"
        },
        {
          "quantity": "3 tsp",
          "name": "tea leaves"
        },
        {
          "quantity": "0.5 cup",
          "name": "milk"
        }
      ],
      "method": "Lorem ipsum dolor sit amet, consectetur adipiscing elit, sed do eiusmod tempor incididunt ut labore et dolore magna aliqua. Ut enim ad minim veniam, quis nostrud exercitation ullamco laboris nisi ut aliquip ex ea commodo consequat. Duis aute irure dolor in reprehenderit in voluptate velit esse cillum dolore eu fugiat nulla pariatur. Excepteur sint occaecat cupidatat non proident, sunt in culpa qui officia deserunt mollit anim id est laborum."
    },

    {
      "id": "classic-chai",
      "name": "Classic Chai",
      "serving": 1,
      "ingredients": [
        {
          "quantity": "1 cup",
          "name": "water"
        },
        {
          "quantity": "1.5 tsp",
          "name": "sugar"
        },
        {
          "quantity": "3 tsp",
          "name": "tea leaves"
        },
        {
          "quantity": "0.5 cup",
          "name": "milk"
        }
      ],
      "method": "Lorem ipsum dolor sit amet, consectetur adipiscing elit, sed do eiusmod tempor incididunt ut labore et dolore magna aliqua. Ut enim ad minim veniam, quis nostrud exercitation ullamco laboris nisi ut aliquip ex ea commodo consequat. Duis aute irure dolor in reprehenderit in voluptate velit esse cillum dolore eu fugiat nulla pariatur. Excepteur sint occaecat cupidatat non proident, sunt in culpa qui officia deserunt mollit anim id est laborum."
    },
    {
      "id": "filter-coffee",
      "name": "Filter Coffee",
      "serving": 1,
      "ingredients": [
        {
          "quantity": "1.5 cup",
          "name": "water"
        },
        {
          "quantity": "2 tsp",
          "name": "sugar"
        },
        {
          "quantity": "1 tbsp",
          "name": "filter coffee powder"
        },
        {
          "quantity": "0.5 cup",
          "name": "milk"
        }
      ],
      "method": "Lorem ipsum dolor sit amet, consectetur adipiscing elit, sed do eiusmod tempor incididunt ut labore et dolore magna aliqua. Ut enim ad minim veniam, quis nostrud exercitation ullamco laboris nisi ut aliquip ex ea commodo consequat. Duis aute irure dolor in reprehenderit in voluptate velit esse cillum dolore eu fugiat nulla pariatur. Excepteur sint occaecat cupidatat non proident, sunt in culpa qui officia deserunt mollit anim id est laborum."
    },
    {
      "id": "masala-chai-spl",
      "name": "Masala Chai Special",
      "serving": 1,
      "ingredients": [
        {
          "quantity": "1 cup",
          "name": "water"
        },
        {
          "quantity": "1.5 tsp",
          "name": "sugar"
        },
        {
          "quantity": "0.25 tsp",
          "name": "cardamom"
        },
        {
          "quantity": "0.25 tsp",
          "name": "clove"
        },
        {
          "quantity": "0.25 tsp",
          "name": "black peppercorn"
        },
        {
          "quantity": "3 tsp",
          "name": "tea leaves"
        },
        {
          "quantity": "0.5 cup",
          "name": "milk"
        }
      ],
      "method": "Lorem ipsum dolor sit amet, consectetur adipiscing elit, sed do eiusmod tempor incididunt ut labore et dolore magna aliqua. Ut enim ad minim veniam, quis nostrud exercitation ullamco laboris nisi ut aliquip ex ea commodo consequat. Duis aute irure dolor in reprehenderit in voluptate velit esse cillum dolore eu fugiat nulla pariatur. Excepteur sint occaecat cupidatat non proident, sunt in culpa qui officia deserunt mollit anim id est laborum."
    },

    {
      "id": "classic-chai-spl",
      "name": "Classic Chai Special",
      "serving": 1,
      "ingredients": [
        {
          "quantity": "1 cup",
          "name": "water"
        },
        {
          "quantity": "1.5 tsp",
          "name": "sugar"
        },
        {
          "quantity": "3 tsp",
          "name": "tea leaves"
        },
        {
          "quantity": "0.5 cup",
          "name": "milk"
        }
      ],
      "method": "Lorem ipsum dolor sit amet, consectetur adipiscing elit, sed do eiusmod tempor incididunt ut labore et dolore magna aliqua. Ut enim ad minim veniam, quis nostrud exercitation ullamco laboris nisi ut aliquip ex ea commodo consequat. Duis aute irure dolor in reprehenderit in voluptate velit esse cillum dolore eu fugiat nulla pariatur. Excepteur sint occaecat cupidatat non proident, sunt in culpa qui officia deserunt mollit anim id est laborum."
    }
  ],
  "starter": [
    {
      "id": "medu-vada",
      "name": "Medu Vada",
      "serving": 1,
      "ingredients": [
        {
          "quantity": "1 cup",
          "name": "urad dal"
        },
        {
          "quantity": "0.3 tsp",
          "name": "salt"
        },
        {
          "quantity": "0.25 tsp",
          "name": "black peppercorn"
        },
        {
          "quantity": "5 grams",
          "name": "green chillis"
        }
      ],
      "method": "Lorem ipsum dolor sit amet, consectetur adipiscing elit, sed do eiusmod tempor incididunt ut labore et dolore magna aliqua. Ut enim ad minim veniam, quis nostrud exercitation ullamco laboris nisi ut aliquip ex ea commodo consequat. Duis aute irure dolor in reprehenderit in voluptate velit esse cillum dolore eu fugiat nulla pariatur. Excepteur sint occaecat cupidatat non proident, sunt in culpa qui officia deserunt mollit anim id est laborum."
    },
    {
      "id": "masala-vada",
      "name": "Masala Vada",
      "serving": 7,
      "ingredients": [
        {
          "quantity": "1 cup",
          "name": "chana dal"
        },
        {
          "quantity": "0.3 tsp",
          "name": "salt"
        },
        {
          "quantity": "0.25 tsp",
          "name": "black peppercorn"
        },
        {
          "quantity": "5 grams",
          "name": "green chillis"
        },
        {
          "quantity": "0.75 tsp",
          "name": "cumin"
        },
        {
          "quantity": "0.75 tsp",
          "name": "fennel seeds"
        }
      ],
      "method": "Lorem ipsum dolor sit amet, consectetur adipiscing elit, sed do eiusmod tempor incididunt ut labore et dolore magna aliqua. Ut enim ad minim veniam, quis nostrud exercitation ullamco laboris nisi ut aliquip ex ea commodo consequat. Duis aute irure dolor in reprehenderit in voluptate velit esse cillum dolore eu fugiat nulla pariatur. Excepteur sint occaecat cupidatat non proident, sunt in culpa qui officia deserunt mollit anim id est laborum."
    },
    {
      "id": "veg-cutlet",
      "name": "Veg Cutlet",
      "serving": 3,
      "ingredients": [
        {
          "quantity": "2 cup",
          "name": "potatos"
        },
        {
          "quantity": "0.5 cup",
          "name": "green peas"
        },
        {
          "quantity": "1 cup",
          "name": "carrot"
        },
        {
          "quantity": "5 grams",
          "name": "green chillis"
        },
        {
          "quantity": "0.25 tsp",
          "name": "garam masala"
        },
        {
          "quantity": "0.5 tsp",
          "name": "salt"
        }
      ],
      "method": "Lorem ipsum dolor sit amet, consectetur adipiscing elit, sed do eiusmod tempor incididunt ut labore et dolore magna aliqua. Ut enim ad minim veniam, quis nostrud exercitation ullamco laboris nisi ut aliquip ex ea commodo consequat. Duis aute irure dolor in reprehenderit in voluptate velit esse cillum dolore eu fugiat nulla pariatur. Excepteur sint occaecat cupidatat non proident, sunt in culpa qui officia deserunt mollit anim id est laborum."
    },
    {
      "id": "medu-vada-spl",
      "name": "Medu Vada Special",
      "serving": 1,
      "ingredients": [
        {
          "quantity": "1 cup",
          "name": "urad dal"
        },
        {
          "quantity": "0.3 tsp",
          "name": "salt"
        },
        {
          "quantity": "0.25 tsp",
          "name": "black peppercorn"
        },
        {
          "quantity": "5 grams",
          "name": "green chillis"
        }
      ],
      "method": "Lorem ipsum dolor sit amet, consectetur adipiscing elit, sed do eiusmod tempor incididunt ut labore et dolore magna aliqua. Ut enim ad minim veniam, quis nostrud exercitation ullamco laboris nisi ut aliquip ex ea commodo consequat. Duis aute irure dolor in reprehenderit in voluptate velit esse cillum dolore eu fugiat nulla pariatur. Excepteur sint occaecat cupidatat non proident, sunt in culpa qui officia deserunt mollit anim id est laborum."
    },
    {
      "id": "masala-vada-spl",
      "name": "Masala Vada Special",
      "serving": 7,
      "ingredients": [
        {
          "quantity": "1 cup",
          "name": "chana dal"
        },
        {
          "quantity": "0.3 tsp",
          "name": "salt"
        },
        {
          "quantity": "0.25 tsp",
          "name": "black peppercorn"
        },
        {
          "quantity": "5 grams",
          "name": "green chillis"
        },
        {
          "quantity": "0.75 tsp",
          "name": "cumin"
        },
        {
          "quantity": "0.75 tsp",
          "name": "fennel seeds"
        }
      ],
      "method": "Lorem ipsum dolor sit amet, consectetur adipiscing elit, sed do eiusmod tempor incididunt ut labore et dolore magna aliqua. Ut enim ad minim veniam, quis nostrud exercitation ullamco laboris nisi ut aliquip ex ea commodo consequat. Duis aute irure dolor in reprehenderit in voluptate velit esse cillum dolore eu fugiat nulla pariatur. Excepteur sint occaecat cupidatat non proident, sunt in culpa qui officia deserunt mollit anim id est laborum."
    }
  ],
  "main": [
    {
      "id": "pongal",
      "name": "Pongal",
      "serving": 6,
      "ingredients": [
        {
          "quantity": "2 cup",
          "name": "potatos"
        },
        {
          "quantity": "0.5 cup",
          "name": "green peas"
        },
        {
          "quantity": "1 cup",
          "name": "carrot"
        },
        {
          "quantity": "5 grams",
          "name": "green chillis"
        },
        {
          "quantity": "0.25 tsp",
          "name": "garam masala"
        },
        {
          "quantity": "0.5 tsp",
          "name": "salt"
        }
      ],
      "method": "Lorem ipsum dolor sit amet, consectetur adipiscing elit, sed do eiusmod tempor incididunt ut labore et dolore magna aliqua. Ut enim ad minim veniam, quis nostrud exercitation ullamco laboris nisi ut aliquip ex ea commodo consequat. Duis aute irure dolor in reprehenderit in voluptate velit esse cillum dolore eu fugiat nulla pariatur. Excepteur sint occaecat cupidatat non proident, sunt in culpa qui officia deserunt mollit anim id est laborum."
    },
    {
      "id": "idli",
      "name": "Ildi",
      "serving": 6,
      "ingredients": [
        {
          "quantity": "2 cup",
          "name": "potatos"
        },
        {
          "quantity": "0.5 cup",
          "name": "green peas"
        },
        {
          "quantity": "1 cup",
          "name": "carrot"
        },
        {
          "quantity": "5 grams",
          "name": "green chillis"
        },
        {
          "quantity": "0.25 tsp",
          "name": "garam masala"
        },
        {
          "quantity": "0.5 tsp",
          "name": "salt"
        }
      ],
      "method": "Lorem ipsum dolor sit amet, consectetur adipiscing elit, sed do eiusmod tempor incididunt ut labore et dolore magna aliqua. Ut enim ad minim veniam, quis nostrud exercitation ullamco laboris nisi ut aliquip ex ea commodo consequat. Duis aute irure dolor in reprehenderit in voluptate velit esse cillum dolore eu fugiat nulla pariatur. Excepteur sint occaecat cupidatat non proident, sunt in culpa qui officia deserunt mollit anim id est laborum."
    },
    {
      "id": "masala-dosa",
      "name": "Masala Dosa",
      "serving": 6,
      "ingredients": [
        {
          "quantity": "2 cup",
          "name": "potatos"
        },
        {
          "quantity": "0.5 cup",
          "name": "green peas"
        },
        {
          "quantity": "1 cup",
          "name": "carrot"
        },
        {
          "quantity": "5 grams",
          "name": "green chillis"
        },
        {
          "quantity": "0.25 tsp",
          "name": "garam masala"
        },
        {
          "quantity": "0.5 tsp",
          "name": "salt"
        }
      ],
      "method": "Lorem ipsum dolor sit amet, consectetur adipiscing elit, sed do eiusmod tempor incididunt ut labore et dolore magna aliqua. Ut enim ad minim veniam, quis nostrud exercitation ullamco laboris nisi ut aliquip ex ea commodo consequat. Duis aute irure dolor in reprehenderit in voluptate velit esse cillum dolore eu fugiat nulla pariatur. Excepteur sint occaecat cupidatat non proident, sunt in culpa qui officia deserunt mollit anim id est laborum."
    },
    {
      "id": "pongal-spl",
      "name": "Pongal Special",
      "serving": 6,
      "ingredients": [
        {
          "quantity": "2 cup",
          "name": "potatos"
        },
        {
          "quantity": "0.5 cup",
          "name": "green peas"
        },
        {
          "quantity": "1 cup",
          "name": "carrot"
        },
        {
          "quantity": "5 grams",
          "name": "green chillis"
        },
        {
          "quantity": "0.25 tsp",
          "name": "garam masala"
        },
        {
          "quantity": "0.5 tsp",
          "name": "salt"
        }
      ],
      "method": "Lorem ipsum dolor sit amet, consectetur adipiscing elit, sed do eiusmod tempor incididunt ut labore et dolore magna aliqua. Ut enim ad minim veniam, quis nostrud exercitation ullamco laboris nisi ut aliquip ex ea commodo consequat. Duis aute irure dolor in reprehenderit in voluptate velit esse cillum dolore eu fugiat nulla pariatur. Excepteur sint occaecat cupidatat non proident, sunt in culpa qui officia deserunt mollit anim id est laborum."
    },
    {
      "id": "idli-spl",
      "name": "Ildi Special",
      "serving": 6,
      "ingredients": [
        {
          "quantity": "2 cup",
          "name": "potatos"
        },
        {
          "quantity": "0.5 cup",
          "name": "green peas"
        },
        {
          "quantity": "1 cup",
          "name": "carrot"
        },
        {
          "quantity": "5 grams",
          "name": "green chillis"
        },
        {
          "quantity": "0.25 tsp",
          "name": "garam masala"
        },
        {
          "quantity": "0.5 tsp",
          "name": "salt"
        }
      ],
      "method": "Lorem ipsum dolor sit amet, consectetur adipiscing elit, sed do eiusmod tempor incididunt ut labore et dolore magna aliqua. Ut enim ad minim veniam, quis nostrud exercitation ullamco laboris nisi ut aliquip ex ea commodo consequat. Duis aute irure dolor in reprehenderit in voluptate velit esse cillum dolore eu fugiat nulla pariatur. Excepteur sint occaecat cupidatat non proident, sunt in culpa qui officia deserunt mollit anim id est laborum."
    }
  ],
  "dessert": [
    {
      "id": "kulfi",
      "name": "Kulfi",
      "serving": 6,
      "ingredients": [
        {
          "quantity": "2 cup",
          "name": "potatos"
        },
        {
          "quantity": "0.5 cup",
          "name": "green peas"
        },
        {
          "quantity": "1 cup",
          "name": "carrot"
        },
        {
          "quantity": "5 grams",
          "name": "green chillis"
        },
        {
          "quantity": "0.25 tsp",
          "name": "garam masala"
        },
        {
          "quantity": "0.5 tsp",
          "name": "salt"
        }
      ],
      "method": "Lorem ipsum dolor sit amet, consectetur adipiscing elit, sed do eiusmod tempor incididunt ut labore et dolore magna aliqua. Ut enim ad minim veniam, quis nostrud exercitation ullamco laboris nisi ut aliquip ex ea commodo consequat. Duis aute irure dolor in reprehenderit in voluptate velit esse cillum dolore eu fugiat nulla pariatur. Excepteur sint occaecat cupidatat non proident, sunt in culpa qui officia deserunt mollit anim id est laborum."
    },
    {
      "id": "halwa-spl",
      "name": "Halwa Special",
      "serving": 6,
      "ingredients": [
        {
          "quantity": "2 cup",
          "name": "potatos"
        },
        {
          "quantity": "0.5 cup",
          "name": "green peas"
        },
        {
          "quantity": "1 cup",
          "name": "carrot"
        },
        {
          "quantity": "5 grams",
          "name": "green chillis"
        },
        {
          "quantity": "0.25 tsp",
          "name": "garam masala"
        },
        {
          "quantity": "0.5 tsp",
          "name": "salt"
        }
      ],
      "method": "Lorem ipsum dolor sit amet, consectetur adipiscing elit, sed do eiusmod tempor incididunt ut labore et dolore magna aliqua. Ut enim ad minim veniam, quis nostrud exercitation ullamco laboris nisi ut aliquip ex ea commodo consequat. Duis aute irure dolor in reprehenderit in voluptate velit esse cillum dolore eu fugiat nulla pariatur. Excepteur sint occaecat cupidatat non proident, sunt in culpa qui officia deserunt mollit anim id est laborum."
    },
    {
      "id": "gulab-jamun",
      "name": "Gulab Jamun",
      "serving": 6,
      "ingredients": [
        {
          "quantity": "2 cup",
          "name": "potatos"
        },
        {
          "quantity": "0.5 cup",
          "name": "green peas"
        },
        {
          "quantity": "1 cup",
          "name": "carrot"
        },
        {
          "quantity": "5 grams",
          "name": "green chillis"
        },
        {
          "quantity": "0.25 tsp",
          "name": "garam masala"
        },
        {
          "quantity": "0.5 tsp",
          "name": "salt"
        }
      ],
      "method": "Lorem ipsum dolor sit amet, consectetur adipiscing elit, sed do eiusmod tempor incididunt ut labore et dolore magna aliqua. Ut enim ad minim veniam, quis nostrud exercitation ullamco laboris nisi ut aliquip ex ea commodo consequat. Duis aute irure dolor in reprehenderit in voluptate velit esse cillum dolore eu fugiat nulla pariatur. Excepteur sint occaecat cupidatat non proident, sunt in culpa qui officia deserunt mollit anim id est laborum."
    },
    {
      "id": "kulfi-spl",
      "name": "Fried Ice Cream",
      "serving": 6,
      "ingredients": [
        {
          "quantity": "2 cup",
          "name": "potatos"
        },
        {
          "quantity": "0.5 cup",
          "name": "green peas"
        },
        {
          "quantity": "1 cup",
          "name": "carrot"
        },
        {
          "quantity": "5 grams",
          "name": "green chillis"
        },
        {
          "quantity": "0.25 tsp",
          "name": "garam masala"
        },
        {
          "quantity": "0.5 tsp",
          "name": "salt"
        }
      ],
      "method": "Lorem ipsum dolor sit amet, consectetur adipiscing elit, sed do eiusmod tempor incididunt ut labore et dolore magna aliqua. Ut enim ad minim veniam, quis nostrud exercitation ullamco laboris nisi ut aliquip ex ea commodo consequat. Duis aute irure dolor in reprehenderit in voluptate velit esse cillum dolore eu fugiat nulla pariatur. Excepteur sint occaecat cupidatat non proident, sunt in culpa qui officia deserunt mollit anim id est laborum."
    },
    {
      "id": "halwa",
      "name": "Halwa",
      "serving": 6,
      "ingredients": [
        {
          "quantity": "2 cup",
          "name": "potatos"
        },
        {
          "quantity": "0.5 cup",
          "name": "green peas"
        },
        {
          "quantity": "1 cup",
          "name": "carrot"
        },
        {
          "quantity": "5 grams",
          "name": "green chillis"
        },
        {
          "quantity": "0.25 tsp",
          "name": "garam masala"
        },
        {
          "quantity": "0.5 tsp",
          "name": "salt"
        }
      ],
      "method": "Lorem ipsum dolor sit amet, consectetur adipiscing elit, sed do eiusmod tempor incididunt ut labore et dolore magna aliqua. Ut enim ad minim veniam, quis nostrud exercitation ullamco laboris nisi ut aliquip ex ea commodo consequat. Duis aute irure dolor in reprehenderit in voluptate velit esse cillum dolore eu fugiat nulla pariatur. Excepteur sint occaecat cupidatat non proident, sunt in culpa qui officia deserunt mollit anim id est laborum."
    }
  ]
}
